ttoolly_utils/asserts.py
ttoolly_utils/randomizer.py
ttoolly_utils/utils.py
ttoolly_utils-0.1.1.dist-info/licenses/LICENSE.txt
ttoolly_utils-0.1.1.dist-info/METADATA
ttoolly_utils-0.1.1.dist-info/WHEEL
ttoolly_utils-0.1.1.dist-info/top_level.txt
ttoolly_utils-0.1.1.dist-info/RECORD
