Metadata-Version: 2.4
Name: ttoolly-utils
Version: 0.1.1
Summary: useful tools for test development
Home-page: https://github.com/pefremova/ttoolly-utils
Author: Polina Mishchenko
Author-email: polina.v.mishchenko@gmail.com
Classifier: Programming Language :: Python :: 3
Classifier: Programming Language :: Python :: 3.10
Classifier: Programming Language :: Python :: 3.11
Classifier: Programming Language :: Python :: 3.12
Classifier: Programming Language :: Python :: 3.13
Classifier: Topic :: Software Development :: Testing
Classifier: Topic :: Utilities
Requires-Python: >=3.10
License-File: LICENSE.txt
Provides-Extra: images
Requires-Dist: Pillow>=11.2; extra == "images"
Dynamic: author
Dynamic: author-email
Dynamic: classifier
Dynamic: description
Dynamic: description-content-type
Dynamic: home-page
Dynamic: license-file
Dynamic: provides-extra
Dynamic: requires-python
Dynamic: summary
